[
    { "vaccname" : "Typhoid",
      "Manufact" : "Pfizer",
      "date"     : "11 Nov 2020",
      "type"     : "Injectible",
      "displaytype" : "Type05"
    },
    { "vaccname" : "PCV",
      "Manufact" : "Novartis",
      "date"     : "11 Aug 2020",
      "type"     : "Injectible",
      "displaytype" : "Type05"
    },
    { "vaccname" : "AIDS",
      "Manufact" : "Serum Institute",
      "date"     : "11 Oct 2020",
      "type"     : "Injectible",
      "displaytype" : "Type05"
    },
    { "vaccname" : "Polio",
      "Manufact" : "Any",
      "date"     : "11 Jan 2020",
      "type"     : "Oral",
      "displaytype" : "Type03"
    },
    { "vaccname" : "Hepatitus",
      "Manufact" : "Roche",
      "date"     : "11 Feb 2021",
      "type"     : "Injectible",
      "displaytype" : "Type05"
    },
     { "vaccname" : "Hepatitus B",
      "Manufact" : "Roche",
      "date"     : "11 Feb 2021",
      "type"     : "Injectible",
      "displaytype" : "Type05"
    },
     { "vaccname" : "Flu",
      "Manufact" : "Merck",
      "date"     : "11 Apr 2021",
      "type"     : "Drop",
      "displaytype" : "Type01"
    },
    { "vaccname" : "CPV",
      "Manufact" : "Serum Institute",
      "date"     : "11 June 2021",
      "type"     : "Injectible",
      "displaytype" : "Type05"
    }
]